{
    "id": "clockmaker",
    "name": "Clockmaker",
    "edition": "snv",
    "team": "townsfolk",
    "firstNight": 40,
    "firstNightReminder": "Show the hand signal for the number (1, 2, 3, etc.) of places from Demon to closest Minion.",
    "otherNight": 0,
    "otherNightReminder": "",
    "reminders": [],
    "setup": false,
    "ability": "You start knowing how many steps from the Demon to its nearest Minion.",
    "image": "/build/img/icons/townsfolk/clockmaker.png",
    "icon": "clockmaker.png",
    "home_script": "experimental",
    "type": "townsfolk"
}